main.py
weather_aurelius_mcp_001-0.1.1.dist-info/METADATA
weather_aurelius_mcp_001-0.1.1.dist-info/WHEEL
weather_aurelius_mcp_001-0.1.1.dist-info/entry_points.txt
weather_aurelius_mcp_001-0.1.1.dist-info/top_level.txt
weather_aurelius_mcp_001-0.1.1.dist-info/RECORD
